{
  "get_result": {
    "gvgResult": {
      "battleNum": 603,
      "battleStartTime": 1632510000,
      "battleEndTime": 1632511199,
      "gvgDataId": 2329027,
      "gvgTitle": "Server/typeMap.gvgOutBattle.getResultRes.gvgTitle",
      "partySequence": 2,
      "selfFavoriteAkbMember": 0,
      "selfGuildDataId": 3607,
      "selfGuildName": "Mindless",
      "selfTotalGuildPoint": 0,
      "selfComboCount": 0,
      "selfSiegeWinCount": 0,
      "enemyFavoriteAkbMember": 0,
      "enemyGuildDataId": 7107,
      "enemyGuildName": "Paradox",
      "enemyTotalGuildPoint": 0,
      "enemyComboCount": 0,
      "enemySiegeWinCount": 0,
      "selfRankUserId": 106160819,
      "selfRankNum": 1,
      "selfRankUserName": "GhostyBoi",
      "selfRankGuildPoint": 0,
      "enemyRankUserId": 122347334,
      "enemyRankNum": 1,
      "enemyRankUserName": "Haru",
      "enemyRankGuildPoint": 0,
      "scheduleNo": 1,
      "selfGuildCountryCode": 0,
      "enemyGuildCountryCode": 0
    },
    "gvgMvpRank": [
      {
        "type": 1,
        "typeName": "イノチ",
        "gvgMvpRankDetailList": [
          {
            "rank": 1,
            "valueA": 0,
            "valueB": 0,
            "userIdA": 106160819,
            "userIdB": 122347334,
            "nameA": "GhostyBoi",
            "nameB": "Haru"
          },
          {
            "rank": 2,
            "valueA": 0,
            "valueB": 0,
            "userIdA": 162850803,
            "userIdB": 247802072,
            "nameA": "Max",
            "nameB": "Slay"
          },
          {
            "rank": 3,
            "valueA": 0,
            "valueB": 0,
            "userIdA": 178901344,
            "userIdB": 275591486,
            "nameA": "Kaio",
            "nameB": "Astaroi"
          },
          {
            "rank": 4,
            "valueA": 0,
            "valueB": 0,
            "userIdA": 186609308,
            "userIdB": 378704052,
            "nameA": "DioW",
            "nameB": "Tirez"
          },
          {
            "rank": 5,
            "valueA": 0,
            "valueB": 0,
            "userIdA": 188863573,
            "userIdB": 406787546,
            "nameA": "Guilty",
            "nameB": "Miztaro"
          }
        ]
      },
      {
        "type": 2,
        "typeName": "回復",
        "gvgMvpRankDetailList": [
          {
            "rank": 1,
            "valueA": 0,
            "valueB": 0,
            "userIdA": 0,
            "userIdB": 0,
            "nameA": "",
            "nameB": ""
          },
          {
            "rank": 2,
            "valueA": 0,
            "valueB": 0,
            "userIdA": 0,
            "userIdB": 0,
            "nameA": "",
            "nameB": ""
          },
          {
            "rank": 3,
            "valueA": 0,
            "valueB": 0,
            "userIdA": 0,
            "userIdB": 0,
            "nameA": "",
            "nameB": ""
          },
          {
            "rank": 4,
            "valueA": 0,
            "valueB": 0,
            "userIdA": 0,
            "userIdB": 0,
            "nameA": "",
            "nameB": ""
          },
          {
            "rank": 5,
            "valueA": 0,
            "valueB": 0,
            "userIdA": 0,
            "userIdB": 0,
            "nameA": "",
            "nameB": ""
          }
        ]
      },
      {
        "type": 3,
        "typeName": "味方攻撃力支援",
        "gvgMvpRankDetailList": [
          {
            "rank": 1,
            "valueA": 0,
            "valueB": 0,
            "userIdA": 0,
            "userIdB": 0,
            "nameA": "",
            "nameB": ""
          },
          {
            "rank": 2,
            "valueA": 0,
            "valueB": 0,
            "userIdA": 0,
            "userIdB": 0,
            "nameA": "",
            "nameB": ""
          },
          {
            "rank": 3,
            "valueA": 0,
            "valueB": 0,
            "userIdA": 0,
            "userIdB": 0,
            "nameA": "",
            "nameB": ""
          },
          {
            "rank": 4,
            "valueA": 0,
            "valueB": 0,
            "userIdA": 0,
            "userIdB": 0,
            "nameA": "",
            "nameB": ""
          },
          {
            "rank": 5,
            "valueA": 0,
            "valueB": 0,
            "userIdA": 0,
            "userIdB": 0,
            "nameA": "",
            "nameB": ""
          }
        ]
      },
      {
        "type": 4,
        "typeName": "味方防御力支援",
        "gvgMvpRankDetailList": [
          {
            "rank": 1,
            "valueA": 0,
            "valueB": 0,
            "userIdA": 0,
            "userIdB": 0,
            "nameA": "",
            "nameB": ""
          },
          {
            "rank": 2,
            "valueA": 0,
            "valueB": 0,
            "userIdA": 0,
            "userIdB": 0,
            "nameA": "",
            "nameB": ""
          },
          {
            "rank": 3,
            "valueA": 0,
            "valueB": 0,
            "userIdA": 0,
            "userIdB": 0,
            "nameA": "",
            "nameB": ""
          },
          {
            "rank": 4,
            "valueA": 0,
            "valueB": 0,
            "userIdA": 0,
            "userIdB": 0,
            "nameA": "",
            "nameB": ""
          },
          {
            "rank": 5,
            "valueA": 0,
            "valueB": 0,
            "userIdA": 0,
            "userIdB": 0,
            "nameA": "",
            "nameB": ""
          }
        ]
      },
      {
        "type": 5,
        "typeName": "敵攻撃力妨害",
        "gvgMvpRankDetailList": [
          {
            "rank": 1,
            "valueA": 0,
            "valueB": 0,
            "userIdA": 0,
            "userIdB": 0,
            "nameA": "",
            "nameB": ""
          },
          {
            "rank": 2,
            "valueA": 0,
            "valueB": 0,
            "userIdA": 0,
            "userIdB": 0,
            "nameA": "",
            "nameB": ""
          },
          {
            "rank": 3,
            "valueA": 0,
            "valueB": 0,
            "userIdA": 0,
            "userIdB": 0,
            "nameA": "",
            "nameB": ""
          },
          {
            "rank": 4,
            "valueA": 0,
            "valueB": 0,
            "userIdA": 0,
            "userIdB": 0,
            "nameA": "",
            "nameB": ""
          },
          {
            "rank": 5,
            "valueA": 0,
            "valueB": 0,
            "userIdA": 0,
            "userIdB": 0,
            "nameA": "",
            "nameB": ""
          }
        ]
      },
      {
        "type": 6,
        "typeName": "敵防御力妨害",
        "gvgMvpRankDetailList": [
          {
            "rank": 1,
            "valueA": 0,
            "valueB": 0,
            "userIdA": 0,
            "userIdB": 0,
            "nameA": "",
            "nameB": ""
          },
          {
            "rank": 2,
            "valueA": 0,
            "valueB": 0,
            "userIdA": 0,
            "userIdB": 0,
            "nameA": "",
            "nameB": ""
          },
          {
            "rank": 3,
            "valueA": 0,
            "valueB": 0,
            "userIdA": 0,
            "userIdB": 0,
            "nameA": "",
            "nameB": ""
          },
          {
            "rank": 4,
            "valueA": 0,
            "valueB": 0,
            "userIdA": 0,
            "userIdB": 0,
            "nameA": "",
            "nameB": ""
          },
          {
            "rank": 5,
            "valueA": 0,
            "valueB": 0,
            "userIdA": 0,
            "userIdB": 0,
            "nameA": "",
            "nameB": ""
          }
        ]
      },
      {
        "type": 7,
        "typeName": "コンボ",
        "gvgMvpRankDetailList": [
          {
            "rank": 1,
            "valueA": 0,
            "valueB": 0,
            "userIdA": 0,
            "userIdB": 0,
            "nameA": "",
            "nameB": ""
          },
          {
            "rank": 2,
            "valueA": 0,
            "valueB": 0,
            "userIdA": 0,
            "userIdB": 0,
            "nameA": "",
            "nameB": ""
          },
          {
            "rank": 3,
            "valueA": 0,
            "valueB": 0,
            "userIdA": 0,
            "userIdB": 0,
            "nameA": "",
            "nameB": ""
          },
          {
            "rank": 4,
            "valueA": 0,
            "valueB": 0,
            "userIdA": 0,
            "userIdB": 0,
            "nameA": "",
            "nameB": ""
          },
          {
            "rank": 5,
            "valueA": 0,
            "valueB": 0,
            "userIdA": 0,
            "userIdB": 0,
            "nameA": "",
            "nameB": ""
          }
        ]
      }
    ],
    "gvgUltimateArtInfo": {
      "gvgDataId": 2329027,
      "gvgUltimateArtDataList": [
        {
          "artMstId": 7,
          "ultimateArtMethodMstId": 7,
          "guildACount": 0,
          "guildBCount": 0
        },
        {
          "artMstId": 1,
          "ultimateArtMethodMstId": 1,
          "guildACount": 0,
          "guildBCount": 0
        }
      ]
    }
  },
  "get_battle_user_list": {
    "battleNum": 603,
    "gvgDataId": 2329027,
    "guildDataIdA": 3607,
    "guildDataIdB": 7107,
    "guildDataNameA": "Mindless",
    "guildDataNameB": "Paradox",
    "guildDataLevelA": 50,
    "guildDataLevelB": 43,
    "guildDataRankA": 0,
    "guildDataRankB": 0,
    "guildMemberA": [
      {
        "userId": 162850803,
        "name": "Max",
        "characterMstId": 102,
        "level": 91,
        "totalPower": 79083,
        "maxHp": 13624
      },
      {
        "userId": 530037340,
        "name": "Dina",
        "characterMstId": 6,
        "level": 35,
        "totalPower": 12790,
        "maxHp": 4831
      },
      {
        "userId": 607502937,
        "name": "Astra",
        "characterMstId": 3,
        "level": 8,
        "totalPower": 5556,
        "maxHp": 1000
      },
      {
        "userId": 298613804,
        "name": "DarkAz",
        "characterMstId": 38,
        "level": 91,
        "totalPower": 80610,
        "maxHp": 14624
      },
      {
        "userId": 480542285,
        "name": "Midarin",
        "characterMstId": 36,
        "level": 72,
        "totalPower": 52716,
        "maxHp": 10904
      },
      {
        "userId": 837992644,
        "name": "Exleos",
        "characterMstId": 159,
        "level": 57,
        "totalPower": 37042,
        "maxHp": 8329
      },
      {
        "userId": 424339726,
        "name": "Siema",
        "characterMstId": 36,
        "level": 25,
        "totalPower": 19679,
        "maxHp": 3532
      },
      {
        "userId": 628142319,
        "name": "Kraine",
        "characterMstId": 8,
        "level": 54,
        "totalPower": 46170,
        "maxHp": 7833
      },
      {
        "userId": 186609308,
        "name": "DioW",
        "characterMstId": 121,
        "level": 52,
        "totalPower": 28662,
        "maxHp": 7154
      },
      {
        "userId": 106160819,
        "name": "GhostyBoi",
        "characterMstId": 15,
        "level": 57,
        "totalPower": 47381,
        "maxHp": 8229
      },
      {
        "userId": 193289944,
        "name": "Lambchop",
        "characterMstId": 94,
        "level": 18,
        "totalPower": 11910,
        "maxHp": 2336
      },
      {
        "userId": 775526341,
        "name": "N.E.R.D",
        "characterMstId": 444,
        "level": 81,
        "totalPower": 50838,
        "maxHp": 12698
      },
      {
        "userId": 178901344,
        "name": "Kaio",
        "characterMstId": 32,
        "level": 28,
        "totalPower": 17286,
        "maxHp": 4051
      },
      {
        "userId": 188863573,
        "name": "Guilty",
        "characterMstId": 39,
        "level": 36,
        "totalPower": 26688,
        "maxHp": 4942
      },
      {
        "userId": 409563292,
        "name": "Mantovas",
        "characterMstId": 243,
        "level": 27,
        "totalPower": 23408,
        "maxHp": 4465
      }
    ],
    "guildMemberB": [
      {
        "userId": 886615782,
        "name": "Dodo",
        "characterMstId": 3,
        "level": 44,
        "totalPower": 48030,
        "maxHp": 6020
      },
      {
        "userId": 732361841,
        "name": "Scope",
        "characterMstId": 5,
        "level": 34,
        "totalPower": 33527,
        "maxHp": 4691
      },
      {
        "userId": 247802072,
        "name": "Slay",
        "characterMstId": 3,
        "level": 32,
        "totalPower": 29925,
        "maxHp": 4534
      },
      {
        "userId": 378704052,
        "name": "Tirez",
        "characterMstId": 38,
        "level": 86,
        "totalPower": 84852,
        "maxHp": 12606
      },
      {
        "userId": 695578064,
        "name": "Raiden",
        "characterMstId": 25,
        "level": 74,
        "totalPower": 57835,
        "maxHp": 10382
      },
      {
        "userId": 723696379,
        "name": "2B",
        "characterMstId": 38,
        "level": 19,
        "totalPower": 48201,
        "maxHp": 2605
      },
      {
        "userId": 275591486,
        "name": "Astaroi",
        "characterMstId": 36,
        "level": 64,
        "totalPower": 42225,
        "maxHp": 8790
      },
      {
        "userId": 755390225,
        "name": "Fredrick",
        "characterMstId": 159,
        "level": 42,
        "totalPower": 34015,
        "maxHp": 5775
      },
      {
        "userId": 446446642,
        "name": "Thall",
        "characterMstId": 21,
        "level": 29,
        "totalPower": 24326,
        "maxHp": 4508
      },
      {
        "userId": 771831128,
        "name": "Carmine",
        "characterMstId": 38,
        "level": 32,
        "totalPower": 18734,
        "maxHp": 4684
      },
      {
        "userId": 122347334,
        "name": "Haru",
        "characterMstId": 18,
        "level": 21,
        "totalPower": 26697,
        "maxHp": 2593
      },
      {
        "userId": 515331696,
        "name": "Raiden",
        "characterMstId": 27,
        "level": 41,
        "totalPower": 38453,
        "maxHp": 5620
      },
      {
        "userId": 807068112,
        "name": "Lilly",
        "characterMstId": 23,
        "level": 25,
        "totalPower": 23654,
        "maxHp": 3532
      },
      {
        "userId": 406787546,
        "name": "Miztaro",
        "characterMstId": 22,
        "level": 28,
        "totalPower": 23002,
        "maxHp": 4101
      }
    ]
  }
}