{
  "get_result": {
    "gvgResult": {
      "battleNum": 101,
      "battleStartTime": 1629039600,
      "battleEndTime": 1629040799,
      "gvgDataId": 2216161,
      "gvgTitle": "Server/typeMap.gvgOutBattle.getResultRes.gvgTitle",
      "partySequence": 2,
      "selfFavoriteAkbMember": 0,
      "selfGuildDataId": 48205,
      "selfGuildName": "Daydreamer",
      "selfTotalGuildPoint": 4138194,
      "selfComboCount": 1686,
      "selfSiegeWinCount": 8,
      "enemyFavoriteAkbMember": 0,
      "enemyGuildDataId": 39092,
      "enemyGuildName": "Kasai|火災",
      "enemyTotalGuildPoint": 562874,
      "enemyComboCount": 1225,
      "enemySiegeWinCount": 0,
      "selfRankUserId": 886338464,
      "selfRankNum": 1,
      "selfRankUserName": "我是Bloob❀ぺこ",
      "selfRankGuildPoint": 1325465,
      "enemyRankUserId": 538655963,
      "enemyRankNum": 1,
      "enemyRankUserName": "Turtle|火災",
      "enemyRankGuildPoint": 421333,
      "scheduleNo": 1,
      "selfGuildCountryCode": 0,
      "enemyGuildCountryCode": 0
    },
    "gvgMvpRank": [
      {
        "type": 1,
        "typeName": "イノチ",
        "gvgMvpRankDetailList": [
          {
            "rank": 1,
            "valueA": 1325465,
            "valueB": 421333,
            "userIdA": 886338464,
            "userIdB": 538655963,
            "nameA": "我是Bloob❀ぺこ",
            "nameB": "Turtle|火災"
          },
          {
            "rank": 2,
            "valueA": 818053,
            "valueB": 377588,
            "userIdA": 945805018,
            "userIdB": 336376359,
            "nameA": "Maximilian",
            "nameB": "Rojovolas"
          },
          {
            "rank": 3,
            "valueA": 457297,
            "valueB": 334378,
            "userIdA": 801687852,
            "userIdB": 328722456,
            "nameA": "DaijobuGGs",
            "nameB": "MrBrando"
          },
          {
            "rank": 4,
            "valueA": 386236,
            "valueB": 162042,
            "userIdA": 311155260,
            "userIdB": 156174607,
            "nameA": "Tamuko",
            "nameB": "IRAH|火災"
          },
          {
            "rank": 5,
            "valueA": 374449,
            "valueB": 617,
            "userIdA": 658397897,
            "userIdB": 606142365,
            "nameA": "Juddy",
            "nameB": "Neo"
          }
        ]
      },
      {
        "type": 2,
        "typeName": "回復",
        "gvgMvpRankDetailList": [
          {
            "rank": 1,
            "valueA": 11346017,
            "valueB": 11438048,
            "userIdA": 335076343,
            "userIdB": 864927173,
            "nameA": "Melesie",
            "nameB": "winterbrrr"
          },
          {
            "rank": 2,
            "valueA": 8672952,
            "valueB": 8627212,
            "userIdA": 519357658,
            "userIdB": 969474209,
            "nameA": "NeoCrimson",
            "nameB": "Eri|火災"
          },
          {
            "rank": 3,
            "valueA": 7026734,
            "valueB": 6651663,
            "userIdA": 595872065,
            "userIdB": 702961283,
            "nameA": "Fuyune<3",
            "nameB": "Rue"
          },
          {
            "rank": 4,
            "valueA": 107164,
            "valueB": 1248191,
            "userIdA": 886338464,
            "userIdB": 122399458,
            "nameA": "我是Bloob❀ぺこ",
            "nameB": "Galadyer"
          },
          {
            "rank": 5,
            "valueA": 42890,
            "valueB": 401019,
            "userIdA": 658397897,
            "userIdB": 634988856,
            "nameA": "Juddy",
            "nameB": "Kaya"
          }
        ]
      },
      {
        "type": 3,
        "typeName": "味方攻撃力支援",
        "gvgMvpRankDetailList": [
          {
            "rank": 1,
            "valueA": 835576,
            "valueB": 1118219,
            "userIdA": 898672025,
            "userIdB": 437661206,
            "nameA": "colonel",
            "nameB": "MyLilPog"
          },
          {
            "rank": 2,
            "valueA": 533725,
            "valueB": 493059,
            "userIdA": 130144213,
            "userIdB": 634988856,
            "nameA": "Azami",
            "nameB": "Kaya"
          },
          {
            "rank": 3,
            "valueA": 481034,
            "valueB": 468752,
            "userIdA": 252654652,
            "userIdB": 635885573,
            "nameA": "Xameria",
            "nameB": "Mitsuki|火災"
          },
          {
            "rank": 4,
            "valueA": 189021,
            "valueB": 275057,
            "userIdA": 594178109,
            "userIdB": 606142365,
            "nameA": "Jeanne",
            "nameB": "Neo"
          },
          {
            "rank": 5,
            "valueA": 95956,
            "valueB": 128001,
            "userIdA": 917156829,
            "userIdB": 864927173,
            "nameA": ":3",
            "nameB": "winterbrrr"
          }
        ]
      },
      {
        "type": 4,
        "typeName": "味方防御力支援",
        "gvgMvpRankDetailList": [
          {
            "rank": 1,
            "valueA": 1128673,
            "valueB": 1129581,
            "userIdA": 898672025,
            "userIdB": 437661206,
            "nameA": "colonel",
            "nameB": "MyLilPog"
          },
          {
            "rank": 2,
            "valueA": 409466,
            "valueB": 559093,
            "userIdA": 252654652,
            "userIdB": 635885573,
            "nameA": "Xameria",
            "nameB": "Mitsuki|火災"
          },
          {
            "rank": 3,
            "valueA": 308452,
            "valueB": 537500,
            "userIdA": 594178109,
            "userIdB": 606142365,
            "nameA": "Jeanne",
            "nameB": "Neo"
          },
          {
            "rank": 4,
            "valueA": 278726,
            "valueB": 533681,
            "userIdA": 130144213,
            "userIdB": 634988856,
            "nameA": "Azami",
            "nameB": "Kaya"
          },
          {
            "rank": 5,
            "valueA": 125852,
            "valueB": 113755,
            "userIdA": 335076343,
            "userIdB": 702961283,
            "nameA": "Melesie",
            "nameB": "Rue"
          }
        ]
      },
      {
        "type": 5,
        "typeName": "敵攻撃力妨害",
        "gvgMvpRankDetailList": [
          {
            "rank": 1,
            "valueA": 1355265,
            "valueB": 618002,
            "userIdA": 594178109,
            "userIdB": 104634313,
            "nameA": "Jeanne",
            "nameB": "Gery"
          },
          {
            "rank": 2,
            "valueA": 533236,
            "valueB": 447806,
            "userIdA": 178311698,
            "userIdB": 242417055,
            "nameA": "Charioce",
            "nameB": "Hideki"
          },
          {
            "rank": 3,
            "valueA": 229812,
            "valueB": 417568,
            "userIdA": 557593123,
            "userIdB": 437661206,
            "nameA": "Derpy",
            "nameB": "MyLilPog"
          },
          {
            "rank": 4,
            "valueA": 208833,
            "valueB": 140082,
            "userIdA": 252654652,
            "userIdB": 122399458,
            "nameA": "Xameria",
            "nameB": "Galadyer"
          },
          {
            "rank": 5,
            "valueA": 170311,
            "valueB": 67249,
            "userIdA": 917156829,
            "userIdB": 538655963,
            "nameA": ":3",
            "nameB": "Turtle|火災"
          }
        ]
      },
      {
        "type": 6,
        "typeName": "敵防御力妨害",
        "gvgMvpRankDetailList": [
          {
            "rank": 1,
            "valueA": 1431696,
            "valueB": 1152655,
            "userIdA": 594178109,
            "userIdB": 242417055,
            "nameA": "Jeanne",
            "nameB": "Hideki"
          },
          {
            "rank": 2,
            "valueA": 1320149,
            "valueB": 690658,
            "userIdA": 917156829,
            "userIdB": 104634313,
            "nameA": ":3",
            "nameB": "Gery"
          },
          {
            "rank": 3,
            "valueA": 531709,
            "valueB": 327481,
            "userIdA": 557593123,
            "userIdB": 122399458,
            "nameA": "Derpy",
            "nameB": "Galadyer"
          },
          {
            "rank": 4,
            "valueA": 371334,
            "valueB": 108519,
            "userIdA": 178311698,
            "userIdB": 336376359,
            "nameA": "Charioce",
            "nameB": "Rojovolas"
          },
          {
            "rank": 5,
            "valueA": 191364,
            "valueB": 86770,
            "userIdA": 130144213,
            "userIdB": 437661206,
            "nameA": "Azami",
            "nameB": "MyLilPog"
          }
        ]
      },
      {
        "type": 7,
        "typeName": "コンボ",
        "gvgMvpRankDetailList": [
          {
            "rank": 1,
            "valueA": 288,
            "valueB": 369,
            "userIdA": 945805018,
            "userIdB": 156174607,
            "nameA": "Maximilian",
            "nameB": "IRAH|火災"
          },
          {
            "rank": 2,
            "valueA": 205,
            "valueB": 354,
            "userIdA": 886338464,
            "userIdB": 538655963,
            "nameA": "我是Bloob❀ぺこ",
            "nameB": "Turtle|火災"
          },
          {
            "rank": 3,
            "valueA": 161,
            "valueB": 307,
            "userIdA": 658397897,
            "userIdB": 336376359,
            "nameA": "Juddy",
            "nameB": "Rojovolas"
          },
          {
            "rank": 4,
            "valueA": 147,
            "valueB": 163,
            "userIdA": 130144213,
            "userIdB": 328722456,
            "nameA": "Azami",
            "nameB": "MrBrando"
          },
          {
            "rank": 5,
            "valueA": 144,
            "valueB": 30,
            "userIdA": 898672025,
            "userIdB": 606142365,
            "nameA": "colonel",
            "nameB": "Neo"
          }
        ]
      }
    ],
    "gvgUltimateArtInfo": {
      "gvgDataId": 2216161,
      "gvgUltimateArtDataList": [
        {
          "artMstId": 11,
          "ultimateArtMethodMstId": 11,
          "guildACount": 75,
          "guildBCount": 55
        },
        {
          "artMstId": 29,
          "ultimateArtMethodMstId": 29,
          "guildACount": 75,
          "guildBCount": 55
        }
      ]
    }
  },
  "get_battle_user_list": {
    "battleNum": 101,
    "gvgDataId": 2216161,
    "guildDataIdA": 48205,
    "guildDataIdB": 39092,
    "guildDataNameA": "Daydreamer",
    "guildDataNameB": "Kasai|火災",
    "guildDataLevelA": 100,
    "guildDataLevelB": 98,
    "guildDataRankA": 2,
    "guildDataRankB": 2,
    "guildMemberA": [
      {
        "userId": 311155260,
        "name": "Tamuko",
        "characterMstId": 103,
        "level": 183,
        "totalPower": 221739,
        "maxHp": 53585
      },
      {
        "userId": 658397897,
        "name": "Juddy",
        "characterMstId": 109,
        "level": 198,
        "totalPower": 218934,
        "maxHp": 53330
      },
      {
        "userId": 886338464,
        "name": "我是Bloob❀ぺこ",
        "characterMstId": 48,
        "level": 201,
        "totalPower": 293971,
        "maxHp": 68645
      },
      {
        "userId": 801687852,
        "name": "DaijobuGGs",
        "characterMstId": 48,
        "level": 200,
        "totalPower": 241164,
        "maxHp": 59655
      },
      {
        "userId": 945805018,
        "name": "Maximilian",
        "characterMstId": 48,
        "level": 197,
        "totalPower": 224838,
        "maxHp": 54018
      },
      {
        "userId": 252654652,
        "name": "Xameria",
        "characterMstId": 53,
        "level": 175,
        "totalPower": 208195,
        "maxHp": 51140
      },
      {
        "userId": 898672025,
        "name": "colonel",
        "characterMstId": 114,
        "level": 189,
        "totalPower": 207028,
        "maxHp": 51034
      },
      {
        "userId": 130144213,
        "name": "Azami",
        "characterMstId": 116,
        "level": 122,
        "totalPower": 172138,
        "maxHp": 28040
      },
      {
        "userId": 594178109,
        "name": "Jeanne",
        "characterMstId": 389,
        "level": 205,
        "totalPower": 234584,
        "maxHp": 56765
      },
      {
        "userId": 917156829,
        "name": ":3",
        "characterMstId": 489,
        "level": 183,
        "totalPower": 195621,
        "maxHp": 50185
      },
      {
        "userId": 557593123,
        "name": "Derpy",
        "characterMstId": 520,
        "level": 144,
        "totalPower": 189007,
        "maxHp": 42455
      },
      {
        "userId": 178311698,
        "name": "Charioce",
        "characterMstId": 93,
        "level": 126,
        "totalPower": 124279,
        "maxHp": 27280
      },
      {
        "userId": 335076343,
        "name": "Melesie",
        "characterMstId": 85,
        "level": 215,
        "totalPower": 235741,
        "maxHp": 64327
      },
      {
        "userId": 519357658,
        "name": "NeoCrimson",
        "characterMstId": 85,
        "level": 188,
        "totalPower": 223120,
        "maxHp": 54625
      },
      {
        "userId": 595872065,
        "name": "Fuyune<3",
        "characterMstId": 85,
        "level": 192,
        "totalPower": 221124,
        "maxHp": 55613
      }
    ],
    "guildMemberB": [
      {
        "userId": 538655963,
        "name": "Turtle|火災",
        "characterMstId": 103,
        "level": 196,
        "totalPower": 244591,
        "maxHp": 53106
      },
      {
        "userId": 328722456,
        "name": "MrBrando",
        "characterMstId": 523,
        "level": 195,
        "totalPower": 223538,
        "maxHp": 52845
      },
      {
        "userId": 156174607,
        "name": "IRAH|火災",
        "characterMstId": 390,
        "level": 187,
        "totalPower": 202621,
        "maxHp": 48716
      },
      {
        "userId": 336376359,
        "name": "Rojovolas",
        "characterMstId": 48,
        "level": 198,
        "totalPower": 225534,
        "maxHp": 57280
      },
      {
        "userId": 437661206,
        "name": "MyLilPog",
        "characterMstId": 44,
        "level": 199,
        "totalPower": 210505,
        "maxHp": 53842
      },
      {
        "userId": 634988856,
        "name": "Kaya",
        "characterMstId": 114,
        "level": 174,
        "totalPower": 209643,
        "maxHp": 47268
      },
      {
        "userId": 606142365,
        "name": "Neo",
        "characterMstId": 114,
        "level": 192,
        "totalPower": 192192,
        "maxHp": 52513
      },
      {
        "userId": 635885573,
        "name": "Mitsuki|火災",
        "characterMstId": 114,
        "level": 135,
        "totalPower": 179396,
        "maxHp": 37713
      },
      {
        "userId": 242417055,
        "name": "Hideki",
        "characterMstId": 93,
        "level": 201,
        "totalPower": 216427,
        "maxHp": 52095
      },
      {
        "userId": 104634313,
        "name": "Gery",
        "characterMstId": 93,
        "level": 182,
        "totalPower": 204600,
        "maxHp": 48528
      },
      {
        "userId": 122399458,
        "name": "Galadyer",
        "characterMstId": 67,
        "level": 195,
        "totalPower": 198570,
        "maxHp": 52495
      },
      {
        "userId": 864927173,
        "name": "winterbrrr",
        "characterMstId": 85,
        "level": 199,
        "totalPower": 250355,
        "maxHp": 56492
      },
      {
        "userId": 969474209,
        "name": "Eri|火災",
        "characterMstId": 85,
        "level": 199,
        "totalPower": 233951,
        "maxHp": 58792
      },
      {
        "userId": 702961283,
        "name": "Rue",
        "characterMstId": 85,
        "level": 190,
        "totalPower": 226783,
        "maxHp": 53943
      }
    ]
  }
}